tc_temporal_backend/__init__.py
tc_temporal_backend/client.py
tc_temporal_backend/schema/__init__.py
tc_temporal_backend/schema/hivemind.py
tc_temporal_backend-1.1.4.dist-info/METADATA
tc_temporal_backend-1.1.4.dist-info/WHEEL
tc_temporal_backend-1.1.4.dist-info/top_level.txt
tc_temporal_backend-1.1.4.dist-info/RECORD
