Metadata-Version: 2.4
Name: tc-temporal-backend
Version: 1.1.4
Summary: This repository is TogetherCrew's temporal io python shared codes
Author: Mohammad Amin Dadgar, TogetherCrew
Maintainer: Mohammad Amin Dadgar
Maintainer-email: dadgaramin96@gmail.com
Requires-Dist: pytest>=7.2.0
Requires-Dist: pytest-cov>=4.0.0
Requires-Dist: python-dotenv<2.0.0,>=1.0.0
Requires-Dist: temporalio<2.0.0,>=1.9.0
Requires-Dist: pydantic<3.0.0,>=2.0.0
Dynamic: author
Dynamic: description
Dynamic: maintainer
Dynamic: maintainer-email
Dynamic: requires-dist
Dynamic: summary
